Workbook

Sheet Risk Narrative
A1: RISK NARRATIVE — QUALITATIVE ASSESSMENT
A2: Complete this tab BEFORE rating. The four assessment dropdowns are read by the referral checks on the D&O Worksheet, and are cross-checked against the modifiers you select there. Write 'None identified' rather than leaving a box blank.
A4: 1. COMPANY OVERVIEW
B5: Business description — what the company actually does, key segments, geographic footprint
B6: Operates three container and bulk terminals in Singapore and Malaysia, with a contract logistics arm (warehousing, freight forwarding) across Indonesia and Vietnam. Terminals contribute about 62% of revenue and the large majority of EBITDA; logistics is lower margin and more competitive. Roughly 55% of assets sit outside Singapore. Listed on the Mainboard since 2011; founder family retains 38%.
B11: Year of establishment | C11: 1994
B12: Exchange, board and year of listing | C12: SGX Mainboard, 2011
B13: Listing status | C13: SGX Mainboard listed | D13: A company listed under 24 months carries prospectus liability — check Q16 agrees.
B14: Market capitalisation (S$m) | C14: ='D&O Worksheet'!$C$13 -> 680 | D14: Pulled from Q1 so the two tabs cannot disagree.
B15: Approximate number of employees | C15: 2100
A16: 2. RISK AND ADVERSE INFORMATION
B17: Negative news, last 3 to 5 years — media, analyst notes, short-seller reports, NGO or union action
B18: Q1 2026: profit warning following loss of a major Indonesian terminal contract; share price fell 9% in one session. Business press coverage questioned concentration risk. No short-seller reports identified. Sources: SGXNet announcements, Business Times, Reuters, Google News, checked 4 Aug 2026.
B22: Regulatory actions, investigations or fines — MAS, ACRA, CAD, CPIB, SGX RegCo, and any overseas regulator
B23: One SGX unusual price movement query (Feb 2026), answered same day. No fines, no enforcement action, no ongoing investigation in Singapore or in any operating jurisdiction. Indonesian customs dispute (2023) settled without penalty.
B27: Class actions, securities litigation, shareholder or minority-oppression disputes
B28: None identified. No class action, derivative action or Section 216 minority-oppression application. Two commercial contract disputes in the ordinary course, both below S$2m and unrelated to directors' conduct.
B32: Litigation exposure level | C32: Low | D32: Low / Moderate / High. Read by the referral checks. High refers, and must be matched by a debit on modifier 4.
A33: 3. FINANCIAL ANALYSIS
B34: Figures in S$m | C34: FY2025 | D34: FY2024 | E34: FY2023 | F34: Most recent year first
B35: Total assets | C35: 690 | D35: 664 | E35: 651
B36: Total liabilities | C36: 372 | D36: 359 | E36: 359
B37: Revenue | C37: 412 | D37: 388 | E37: 401
B38: Net profit / (loss) | C38: 21 | D38: 26 | E38: 31
B39: Shareholders' equity (assets less liabilities) | C39: =IFERROR(C35-C36,"") -> 318 | D39: =IFERROR(D35-D36,"") -> 305 | E39: =IFERROR(E35-E36,"") -> 292
B40: Liabilities / assets | C40: =IFERROR(C36/C35,"") -> 0.53913043 | D40: =IFERROR(D36/D35,"") -> 0.54066265 | E40: =IFERROR(E36/E35,"") -> 0.55145929
B41: Net margin | C41: =IFERROR(C38/C37,"") -> 0.050970874 | D41: =IFERROR(D38/D37,"") -> 0.067010309 | E41: =IFERROR(E38/E37,"") -> 0.077306733
B43: Trend commentary — direction of revenue, margin, leverage and cash across the three years
B44: Revenue broadly flat (S$401m to S$412m) but net profit down a third over three years, from S$31m to S$21m; net margin has compressed from 7.7% to 5.1% on terminal fee pressure and higher fuel and labour costs. Liabilities/assets has risen from 0.55 to 0.54 on a larger balance sheet, with borrowings up S$29m to fund the Vietnam warehouse. Operating cash flow remains positive and comfortably covers interest.
B48: Red flags — margin compression, leverage, liquidity, covenants, going-concern or audit emphasis language
B49: Three consecutive years of declining profit is the main concern, together with customer concentration in Indonesia. Leverage is moderate and interest cover adequate. No covenant breach, no going-concern emphasis, unqualified audit opinion, auditor unchanged. Liquidity is satisfactory.
B53: Overall financial strength | C53: Adequate | D53: Strong / Adequate / Weak / Serious concern. Weak or worse refers, and must be matched by a debit on modifier 1.
A54: 4. CORPORATE GOVERNANCE AND MANAGEMENT
B55: Role | C55: Name | D55: Years in role | E55: Capital markets experience | F55: Finance or accounting experience | G55: Legal or regulatory experience | H55: Relevant background and credentials
B56: Chairman | C56: Tan Wei Ming | D56: 14 | E56: Yes | F56: No | G56: No | H56: Founder's son. Career in port operations; no prior listed directorship outside the group.
B57: Chief Executive Officer | C57: Sarah Lim | D57: 6 | E57: Yes | F57: Yes | G57: No | H57: Ex-CFO of a listed regional logistics group; led two rights issues.
B58: Chief Financial Officer | C58: Rajesh Kumar | D58: 4 | E58: Yes | F58: Yes | G58: No | H58: CA (Singapore), ex-Big Four audit partner. No adverse findings.
B59: Audit Committee Chair | C59: Grace Ong | D59: 5 | E59: Yes | F59: Yes | G59: No | H59: FCCA, chairs the AC of one other Mainboard issuer.
B60: Lead Independent Director | C60: David Choo | D60: 9 | E60: Yes | F60: No | G60: Yes | H60: Senior counsel, corporate and regulatory practice.
B61: Company Secretary | C61: Michelle Ng | D61: 7 | E61: No | F61: No | G61: Yes | H61: Chartered secretary, 20 years in listed-company compliance.
B62: Other key officer
B63: Key officers with finance or accounting experience | C63: =COUNTIF(F56:F62,"Yes") -> 3 | D63: A board with nobody who can read a set of accounts is a governance finding in its own right — it refers.
B65: Assessment — strength of the management team, industry depth, listed-company and capital markets experience
B66: Capable and appropriately credentialled. CEO and CFO both have listed-company and capital markets experience; the CFO is a former Big Four partner and the AC chair is a qualified accountant. The chairman is the founder's son with no outside listed directorship, so independent challenge rests largely on the lead independent director and the AC chair.
B70: Governance concerns, board turnover and succession risk, related-party dynamics
B71: Board is 50% independent, not a majority, with a non-independent chairman — below the SGX Code expectation. Recurring interested-person transactions with family-controlled entities are mandated and disclosed but material in aggregate. No CEO or CFO turnover in 24 months. Director tenure is long, which cuts both ways: continuity, but weaker independence over time.
B75: Management team strength | C75: Adequate | D75: Strong / Adequate / Weak. Weak refers, and must be matched by a debit on modifier 2.
B76: Governance concern level | C76: Minor | D76: None / Minor / Material. Material refers, and must be matched by a debit on modifier 2.
B78: Write what you actually found, including where you looked and on what date. 'None identified' after a real search is a finding; a blank box is not. If the narrative and the modifiers on the D&O Worksheet tell different stories, the referral checks will say so — resolve the difference rather than overwriting one of them.

Sheet D&O Worksheet
A1: D&O UNDERWRITING WORKSHEET — SGX-LISTED COMPANY
A2: Fill in the YELLOW cells only; everything grey is calculated. Currency SGD. Complete the Risk Narrative tab FIRST. The entries shown are a worked example for a fictional company — overwrite them.
A4: IDENTIFICATION
B5: Insured (listed entity) | C5: Marina Logistics Holdings Ltd
B6: SGX code and board | C6: M42 / Mainboard
B7: Sector | C7: Marine ports and logistics
B8: Broker and submission date | C8: Example Broking / 4 Aug 2026
A10: PART 1 — THE RISK (20 questions)
B11: Question | C11: Answer | D11: Feeds | E11: Why it matters / how to answer
A12: A. Size and market exposure
B13: 1. Market capitalisation (S$m) | C13: 680 | D13: Base cost | E13: THE EXPOSURE BASE — it caps the plausible size of a securities claim. Closing market cap at the most recent practicable date.
B14: 2. Free float (%) | C14: 0.42 | D14: Mod 3 | E14: A thin float means fewer aggrieved outside holders but sharper price moves and more minority-oppression risk.
B15: 3. Share price movement, last 12 months (%) | C15: -0.18 | D15: Mod 3 | E15: The single best predictor of a securities claim. A fall shortly after upbeat guidance is the classic fact pattern.
B16: 4. Assets or revenue outside Singapore (%) | C16: 0.55 | D16: Mod 4 | E16: An SGX listing with operations elsewhere makes investigation and asset recovery harder. Above 75% refers and suggests a territorial limitation.
A17: B. Financial condition
B18: 5. Net gearing (net debt / equity) | C18: 0.51 | D18: Mod 1 | E18: Above 2.00x is a material debit; above 3.00x refers. Insolvency is the commonest route to a D&O claim in this region.
B19: 6. Profitable in each of the last three financial years? | C19: All three | D19: Mod 1 | E19: Three clean years earns a credit. 'None' means a loss-making issuer — refers, and suggests an insolvency exclusion.
B20: 7. Profit warning, restatement or material adverse announcement in last 12 months? | C20: Yes | D20: Mod 1 / 3 | E20: A restatement is the strongest accounting red flag there is. A Yes suggests a specific matter exclusion.
A21: C. Governance and audit
B22: 8. Independent directors (% of board) | C22: 0.5 | D22: Mod 2 | E22: The SGX Code expects a majority where the chairman is not independent. Below one third, debit hard.
B23: 9. Largest shareholder holding (%) | C23: 0.38 | D23: Mod 2 | E23: Drives interested-person transactions and minority-oppression exposure. Above 15% suggests a major shareholder exclusion; above 30%, an IPT exclusion.
B24: 10. Audit opinion, most recent | C24: Unqualified | D24: Mod 2 | E24: Anything other than unqualified refers.
B25: 11. Change of external auditor in the last 3 years? | C25: No | D25: Mod 2 | E25: Ask WHY. An auditor who resigns mid-engagement is telling you something the accounts are not.
B26: 12. CEO or CFO change in the last 24 months? | C26: No | D26: Mod 2 | E26: An unexplained CFO departure is a recurring precursor to restatement. Get the reason in writing.
A27: D. Regulatory and capital markets
B28: 13. SGX queries received in the last 24 months (number) | C28: 1 | D28: Mod 4 | E28: Count unusual price movement and trade-with-caution queries. Three or more refers.
B29: 14. Watch-list, trading suspension or regulatory investigation? | C29: No | D29: Mod 4 | E29: Covers the SGX watch-list, non-routine suspensions, and any MAS / CAD / ACRA / SGX RegCo matter.
B30: 15. US securities exposure | C30: None | D30: Mod 4 | E30: The largest single driver of D&O severity worldwide. Anything other than None refers and suggests a US securities exclusion.
B31: 16. IPO, RTO or capital raising in the last 24 months? | C31: Placement or rights issue | D31: Mod 4 | E31: An offering document creates prospectus liability. An IPO or RTO refers — consider a public offering exclusion or a separate POSI policy.
A32: E. Claims and insurance history
B33: 17. D&O claims or notifications, last 5 years (number) | C33: 0 | D33: Mod 5 | E33: Any claim at all refers. Ask for the full loss run, not the broker's summary.
B34: 18. Known circumstance disclosed but not yet notified? | C34: No | D34: Mod 5 | E34: A Yes normally means we do not write it until it has been notified to the expiring insurer.
B35: 19. Has any insurer declined, cancelled or non-renewed D&O cover? | C35: No | D35: Mod 5 | E35: Rarely asked, highly informative. Another underwriter has already priced this risk and walked away — find out why.
A36: F. Expiring programme
B37: 20. Expiring premium for the SAME limit and the SAME share (S$) | C37: 55000 | D37: Benchmark | E37: Must be like-for-like. If we wrote 50% last year and 100% this year, gross the expiring figure up first, or the rate change is meaningless. Enter 0 for new business.
A39: PART 2 — THE STRUCTURE
B40: Item | C40: Your selection | D40: Factor | E40: Notes
B41: Base expected loss cost (S$) | C41: =IFERROR(INDEX(Factors!$A$4:$A$12,MATCH(C13,Factors!$B$4:$B$12,1)),"enter Q1") -> 500 to below 1,000 | D41: =IFERROR(INDEX(Factors!$D$4:$D$12,MATCH(C13,Factors!$B$4:$B$12,1)),"enter Q1") -> 25000 | E41: Table A, driven by Q1. This is a LOSS COST, not a premium.
B42: Limit purchased | C42: S$10m | D42: =IFERROR(INDEX(Factors!$B$16:$B$22,MATCH(C42,Factors!$A$16:$A$22,0)),"select") -> 1 | E42: Table B. Increased limit factor, relative to S$10m = 1.00.
B43: Limit in S$m (used by sublimits and referral checks) | D43: =IFERROR(INDEX(Factors!$C$16:$C$22,MATCH(C42,Factors!$A$16:$A$22,0)),0) -> 10 | E43: Read automatically from Table B — nothing to type.
B44: Corporate (Side B / C) retention | C44: SGD 250k | D44: =IFERROR(INDEX(Factors!$C$26:$C$30,MATCH(C44,Factors!$A$26:$A$30,0)),"select") -> 1 | E44: Table C. Side A always attaches at nil retention.
B45: Industry hazard class | C45: Class 2 | D45: =IFERROR(INDEX(Factors!$C$34:$C$38,MATCH(C45,Factors!$A$34:$A$38,0)),"select") -> 1 | E45: Table D. Classify on the actual business, not the GICS label.
A47: PART 3 — THE JUDGEMENT (five modifiers; 1.00 is neutral)
B48: Modifier | C48: Factor | D48: Range | E48: Guidance — the questions that feed it are named
B49: 1. Financial strength | C49: 1.05 | D49: 0.85 – 1.50 | E49: Q5, Q6, Q7. Credit for net cash and three profitable years. Debit for gearing above 2.0x, a broken profit run, or a warning or restatement in the last year.
B50: 2. Governance and ownership | C50: 1.1 | D50: 0.85 – 1.40 | E50: Q8, Q9, Q10, Q11, Q12. Credit for a majority-independent board and a clean audit history. Debit for a dominant controller, an auditor change, or CFO churn.
B51: 3. Share price and float | C51: 1.1 | D51: 0.90 – 1.50 | E51: Q2, Q3. Flat or rising 0.90–1.00. Down 15–35% 1.15–1.30. Down more than 35%, or a fall straight after upbeat guidance, 1.30–1.50.
B52: 4. Regulatory, geography and transactions | C52: 1.1 | D52: 1.00 – 2.00 | E52: Q4, Q13, Q14, Q15, Q16. 1.00 clean and Singapore-centric. Debit for SGX queries, offshore operations, a recent raising, or ADR exposure. Watch-list or investigation 1.50–2.00.
B53: 5. Claims and insurance history | C53: 0.95 | D53: 0.90 – 2.00 | E53: Q17, Q18, Q19. 0.90 five clean years, fully disclosed, never declined. 1.25–1.60 one notification. 1.60–2.00 a paid claim or a shareholder action.
B54: Composite modifier — the five multiplied together | D54: =PRODUCT(C49:C53) -> 1.3276725 | E54: A blank modifier is ignored by this calculation, so Part 6 checks that all five are filled in.
B55: Composite modifier applied — after Table E floor and cap | D55: =MAX(Factors!$C$43,MIN(Factors!$C$44,D54)) -> 1.3276725 | E55: Floor 0.50, cap 3.50. The referral range of 0.70 – 2.00 bites long before the cap does.
A57: PART 4 — COVERAGE TERMS: SUBLIMITS AND EXCLUSIONS
A58: 4A. Sublimits — the sheet suggests, you agree
B59: Sublimit item | C59: Agreed (S$) | D59: Suggested (S$) | E59: Basis and comment
B60: Emergency legal costs (no prior consent) | C60: 250000 | D60: =D43*1000000*0.1 -> 1000000 | E60: 10% of the limit. Lets a director instruct counsel before we have approved it.
B61: Entity investigation and pre-claim inquiry costs | C61: 2500000 | D61: =MIN(D43*1000000*0.25,5000000) -> 2500000 | E61: 25% of limit, capped at S$5m. The most-used extension in Asia — most matters start as an investigation, not a claim.
B62: Entity employment practices liability | C62: 500000 | D62: =MIN(D43*1000000*0.1,500000) -> 500000 | E62: Sublimit it or exclude it. Full-limit entity EPL on a listed company is not standard.
B63: Crisis and public relations costs | C63: 250000 | D63: =MIN(D43*1000000*0.05,250000) -> 250000 | E63: Funds the announcement and the media handling in the first weeks.
B64: Extradition, bail and civil bond costs | C64: 250000 | D64: =MIN(D43*1000000*0.05,250000) -> 250000 | E64: Relevant wherever directors travel or the group operates cross-border.
B65: Reputation protection expenses | C65: 100000 | D65: =MIN(D43*1000000*0.02,100000) -> 100000 | E65: Personal reputation management for an individual director.
B66: Deprivation of assets costs | C66: 100000 | D66: =MIN(D43*1000000*0.02,100000) -> 100000 | E66: Living expenses where a director's assets are frozen.
B67: Side C entity securities cover | C67: 10000000 | D67: =D43*1000000 -> 10000000 | E67: Normally the full limit. Sublimit it only if the securities exposure is the reason you are nervous.
B68: Sublimits are part of, not in addition to, the policy limit. Also agree separately: the extended reporting period, the run-off period for retired directors (six years is the Singapore norm), and the order-of-payments clause putting Side A first.
A70: 4B. Standard exclusions — always present, already priced into the base cost, no decision needed
B71: Fraud and dishonesty (final adjudication) · personal profit or advantage · prior known claims and circumstances · bodily injury and property damage (defence costs normally carved back) · pollution (defence costs carved back) · professional services rendered to clients · insured versus insured (with the usual carve-backs for derivative actions, liquidators and retired directors) · war, terrorism and sanctions · fines and penalties where uninsurable at law.
A74: 4C. Risk-specific exclusions and extensions — the sheet recommends, you decide
B75: Exclusion or extension | C75: Applied? | D75: Recommendation | E75: What it does and when to use it | F75: Premium effect
B76: Major shareholder exclusion (holders above 15%) | C76: Yes | D76: =IF(C23>0.15,"Apply","Not indicated") -> Apply | E76: Q9. Bars claims by a large shareholder who is effectively suing itself. Near-standard for closely held SGX issuers. | F76: =IF(C76="Yes",-0.025,0) -> -0.025
B77: US securities claims exclusion | C77: No | D77: =IF(C30<>"None","Apply","Not indicated") -> Not indicated | E77: Q15. Removes the single largest severity driver. If the insured needs the cover, rate it separately and refer. | F77: =IF(C77="Yes",-0.1,0) -> 0
B78: Public offering / prospectus liability exclusion | C78: No | D78: =IF(C31="IPO or RTO","Apply","Not indicated") -> Not indicated | E78: Q16. Excludes prospectus claims unless a separate POSI policy is bought. Do not leave an IPO silently covered. | F78: =IF(C78="Yes",-0.05,0) -> 0
B79: Specific matter exclusion (the announced adverse event) | C79: Yes | D79: =IF(C20="Yes","Apply","Not indicated") -> Apply | E79: Q7. Carves out the warning or restatement already in the market. Describe the matter precisely — a vague wording is worthless. | F79: =IF(C79="Yes",-0.05,0) -> -0.05
B80: Specific investigation exclusion | C80: No | D80: =IF(C29="Yes","Apply","Not indicated") -> Not indicated | E80: Q14. Carves out a live regulatory matter. Refer before relying on it. | F80: =IF(C80="Yes",-0.05,0) -> 0
B81: Interested-person / related-party transaction exclusion | C81: Yes | D81: =IF(C23>0.3,"Apply","Not indicated") -> Apply | E81: Q9. Where a controlling family transacts with the listed entity, IPT claims are the likeliest loss. | F81: =IF(C81="Yes",-0.05,0) -> -0.05
B82: Territorial limitation to Singapore and named territories | C82: No | D82: =IF(C16>0.75,"Apply","Not indicated") -> Not indicated | E82: Q4. Confines cover to where you can actually defend a claim. | F82: =IF(C82="Yes",-0.075,0) -> 0
B83: Insolvency and creditor claims exclusion | C83: No | D83: =IF(C19="None","Apply","Not indicated") -> Not indicated | E83: Q6. Rare and contentious — it removes cover exactly when directors need it. Refer before offering. | F83: =IF(C83="Yes",-0.05,0) -> 0
B84: Specific prior claims and circumstances exclusion | C84: No | D84: =IF(OR(C33>0,C34="Yes"),"Apply","Not indicated") -> Not indicated | E84: Q17, Q18. Names the known matters so there is no argument later. | F84: =IF(C84="Yes",-0.025,0) -> 0
B85: EXTENSION — full-limit entity investigation costs | C85: No | D85: ="Optional" -> Optional | E85: Removes the 4A sublimit. Commonly asked for; price it, do not give it away. | F85: =IF(C85="Yes",0.05,0) -> 0
B86: EXTENSION — broad-form entity employment practices liability | C86: No | D86: ="Optional" -> Optional | E86: Widens entity EPL beyond the 4A sublimit. | F86: =IF(C86="Yes",0.075,0) -> 0
B87: EXTENSION — 12-month extended reporting period | C87: No | D87: ="Optional" -> Optional | E87: Lets directors notify for a year after expiry. | F87: =IF(C87="Yes",0.05,0) -> 0
B88: EXTENSION — run-off for retired directors beyond six years | C88: No | D88: ="Optional" -> Optional | E88: Longer tail for directors who have already left. | F88: =IF(C88="Yes",0.025,0) -> 0
B89: Coverage terms factor | D89: =MAX(0.7,MIN(1.3,1+SUM(F76:F88))) -> 0.875 | E89: One plus the sum of the effects above, floored at 0.70 and capped at 1.30. Feeds the price in Part 5.
B90: Never apply an exclusion in order to reach a price. Decide what cover is right for the risk, then let the factor do what it does. Every exclusion you apply must appear in the quotation — a coverage restriction the broker discovers at binding is a complaint waiting to happen. The percentages here are illustrative and must be agreed with your wordings and actuarial teams before live use.
A93: PART 5 — THE PRICE
B94: Technical loss cost (S$) | D94: =IFERROR(D41*D42*D44*D45*D55*D89,"complete Parts 1-4") -> 29042.836 | E94: Base cost × limit × retention × hazard × composite modifier × coverage terms.
B95: Permissible loss ratio | C95: 0.55 | E95: What is left after brokerage, expenses and profit margin. 55% assumes roughly 17.5% brokerage, 15% expense, 12.5% margin.
B96: Technical premium (S$) | D96: =IFERROR(D94/C95,"complete Parts 1-4") -> 52805.156 | E96: The technically indicated price at 100%, before any commercial judgement.
B97: Market adjustment factor | C97: 1 | E97: 0.95 – 1.05 is within junior authority. Outside that, refer and record the competing terms in the file note.
B98: Our participation | C98: 1 | E98: Enter 100% if we are writing the whole limit.
B99: Indicated premium — our share (S$) | D99: =IFERROR(D96*C97*C98,"complete Parts 1-4") -> 52805.156
B100: Minimum premium (S$) | D100: =Factors!$C$42 -> 7500 | E100: Table E.
B101: PREMIUM TO QUOTE (S$) | D101: =IF(ISNUMBER(D99),MAX(D99,D100),"complete Parts 1-4") -> 52805.156 | E101: Subject to Part 6 being clear.
B102: Rate change against expiring | D102: =IFERROR(IF(C37=0,"New business",D101/C37-1),"n/a") -> -0.03990625 | E102: Only meaningful if Q20 was entered on the same limit and share. A reduction greater than 10% refers.
B103: Premium per S$1m of our share (S$) | D103: =IFERROR(D101/(D43*C98),"n/a") -> 5280.5156 | E103: Sense-check against recent SGX risks of similar size and sector. If it looks wrong, it probably is.
A105: PART 6 — REFERRAL CHECK (every trigger fires automatically from Parts 1 to 5)
B106: Trigger | C106: Status | D106: Refer to
B107: Sheet incomplete, or an input is out of bounds | C107: =IF(OR(NOT(ISNUMBER(C13)),C13<=0,D42="select",D44="select",D45="select",COUNT(C49:C53)<5,NOT(ISNUMBER(C98)),C98<=0,C98>1,C95<=0.2,C95>=0.9),"YES","No") -> No | D107: Complete before quoting
B108: A Part 1 question has been left unanswered — check all 20 | C108: =IF(COUNTA(C13:C37)<20,"YES","No") -> No | D108: Complete before quoting
B109: A Part 4 sublimit has been left blank | C109: =IF(COUNT(C60:C67)<8,"YES","No") -> No | D109: Complete before quoting
B110: A percentage answer looks mis-keyed — check Q2, Q3, Q4, Q8, Q9 | C110: =IF(OR(C14>1,C16>1,C22>1,C23>1,C15<-1,C15>3,AND(C14>0,C14<0.05),AND(C22>0,C22<0.05),AND(C23>0,C23<0.01)),"YES","No") -> No | D110: Complete before quoting
B111: A modifier is outside its stated range (0.85 - 2.00) | C111: =IF(AND(COUNT(C49:C53)=5,OR(MIN(C49:C53)<0.85,MAX(C49:C53)>2)),"YES","No") -> No | D111: Senior underwriter
...

Sheet Factors
A1: FACTOR TABLES — do not change without sign-off from the Head of Financial Lines
A3: Market cap band (S$m) | B3: Lower bound (S$m) | C3: Upper bound (S$m) | D3: TABLE A — loss cost (S$)
A4: Below 50 | B4: 0 | C4: 50 | D4: 8000
A5: 50 to below 100 | B5: 50 | C5: 100 | D5: 10500
A6: 100 to below 250 | B6: 100 | C6: 250 | D6: 14000
A7: 250 to below 500 | B7: 250 | C7: 500 | D7: 18500
A8: 500 to below 1,000 | B8: 500 | C8: 1000 | D8: 25000
A9: 1,000 to below 2,500 | B9: 1000 | C9: 2500 | D9: 34000
A10: 2,500 to below 5,000 | B10: 2500 | C10: 5000 | D10: 46000
A11: 5,000 to below 10,000 | B11: 5000 | C11: 10000 | D11: 62000
A12: 10,000 and above | B12: 10000 | C12: 999999 | D12: 82000
A13: Lookup uses the lower bound only; the upper bound column is shown for reading. Basis: S$10m limit, SGD 250k retention, Hazard Class 2, 12 months.
A15: TABLE B — limit | B15: Factor | C15: Limit (S$m) | D15: Comment
A16: S$5m | B16: 0.7 | C16: 5
A17: S$10m | B17: 1 | C17: 10
A18: S$15m | B18: 1.22 | C18: 15
A19: S$20m | B19: 1.4 | C19: 20
A20: S$25m | B20: 1.55 | C20: 25
A21: S$30m | B21: 1.68 | C21: 30
A22: S$50m | B22: 2.05 | C22: 50
A23: Relative to S$10m = 1.00. Column C is read by the worksheet for sublimits and referral checks — keep it aligned with column A.
A25: TABLE C — retention | B25: Retention (S$) | C25: Factor | D25: Comment
A26: SGD 100k | B26: 100000 | C26: 1.15 | D26: Low for a listed company
A27: SGD 250k | B27: 250000 | C27: 1 | D27: Benchmark for an SGX mid-cap
A28: SGD 500k | B28: 500000 | C28: 0.9 | D28: Suits above roughly S$1bn
A29: SGD 1m | B29: 1000000 | C29: 0.8 | D29: Large cap
A30: SGD 2.5m | B30: 2500000 | C30: 0.68 | D30: Large cap only — refer
A33: TABLE D — hazard class | B33: Typical SGX sectors | C33: Factor | D33: Comment
A34: Class 1 | B34: REITs, business trusts, utilities, regulated infrastructure | C34: 0.85 | D34: Stable regulated cash flows
A35: Class 2 | B35: Industrials, consumer staples, transport and logistics, telcos | C35: 1 | D35: Benchmark class
A36: Class 3 | B36: Property developers, construction, agri-commodities, healthcare, hospitality | C36: 1.2 | D36: Cyclical, estimate-heavy accounting
A37: Class 4 | B37: Banks and financial services, offshore and marine, oil and gas, mining, technology | C37: 1.45 | D37: Regulatory intensity, volatile earnings
A38: Class 5 | B38: Pre-revenue biotech, digital assets, Catalist shells, recent RTO or SPAC, distressed | C38: 1.75 | D38: Always refer
A41: TABLE E — parameters | C41: Value | D41: Comment
A42: Minimum premium (S$) | C42: 7500 | D42: Applies to our share
A43: Composite modifier floor | C43: 0.5 | D43: Applied in Part 3
A44: Composite modifier cap | C44: 3.5 | D44: Applied in Part 3
